main.py
setup.py
raylinks.egg-info/PKG-INFO
raylinks.egg-info/SOURCES.txt
raylinks.egg-info/dependency_links.txt
raylinks.egg-info/requires.txt
raylinks.egg-info/top_level.txt